{
  "annotations":{"list":[]},
  "editable":true,
  "graphTooltip":1,
  "panels":[
    {"type":"stat","title":"Flux resources not ready","gridPos":{"h":4,"w":8,"x":0,"y":0},"datasource":{"type":"prometheus","uid":"mimir"},"targets":[{"expr":"sum(gotk_resource_info{environment=~\"$environment\",cluster=~\"$cluster\",ready=\"False\"})","refId":"A"}]},
    {"type":"stat","title":"Longhorn degraded volumes","gridPos":{"h":4,"w":8,"x":8,"y":0},"datasource":{"type":"prometheus","uid":"mimir"},"targets":[{"expr":"sum(longhorn_volume_robustness{environment=~\"$environment\",cluster=~\"$cluster\",robustness!=\"healthy\"})","refId":"A"}]},
    {"type":"stat","title":"Certificate renewals pending","gridPos":{"h":4,"w":8,"x":16,"y":0},"datasource":{"type":"prometheus","uid":"mimir"},"targets":[{"expr":"sum(certmanager_certificate_expiration_timestamp_seconds{environment=~\"$environment\",cluster=~\"$cluster\"} - time() < 604800)","refId":"A"}]},
    {"type":"timeseries","title":"Flux reconciliation rate","gridPos":{"h":8,"w":12,"x":0,"y":4},"datasource":{"type":"prometheus","uid":"mimir"},"targets":[{"expr":"sum(rate(gotk_reconcile_duration_seconds_count{environment=~\"$environment\",cluster=~\"$cluster\"}[5m])) by (kind)","legendFormat":"{{kind}}","refId":"A"}]},
    {"type":"timeseries","title":"Longhorn volume state","gridPos":{"h":8,"w":12,"x":12,"y":4},"datasource":{"type":"prometheus","uid":"mimir"},"targets":[{"expr":"sum(longhorn_volume_robustness{environment=~\"$environment\",cluster=~\"$cluster\"}) by (robustness)","legendFormat":"{{robustness}}","refId":"A"}]},
    {"type":"timeseries","title":"Mimir ingestion errors","gridPos":{"h":8,"w":24,"x":0,"y":12},"datasource":{"type":"prometheus","uid":"mimir"},"targets":[{"expr":"sum(rate(prometheus_remote_storage_failed_samples_total{environment=~\"$environment\",cluster=~\"$cluster\"}[5m]))","legendFormat":"failed samples/sec","refId":"A"}]}
  ],
  "refresh":"30s",
  "schemaVersion":39,
  "tags":["flux","longhorn","platform"],
  "templating":{"list":[{"name":"environment","label":"Environment","type":"query","datasource":{"type":"prometheus","uid":"mimir"},"query":"label_values(up, environment)","includeAll":true,"multi":false,"refresh":1,"current":{"text":"All","value":["$__all"]}},{"name":"cluster","label":"Cluster","type":"query","datasource":{"type":"prometheus","uid":"mimir"},"query":"label_values(up{environment=~\"$environment\"}, cluster)","includeAll":true,"multi":false,"refresh":1,"current":{"text":"All","value":["$__all"]}}]},
  "time":{"from":"now-6h","to":"now"},
  "title":"Platform Operations",
  "uid":"platform-operations",
  "version":1
}
